pdfconvertercaller/__init__.py
pdfconvertercaller/browser.py
pdfconvertercaller/definition.py
pdfconvertercaller/locators.py
vidstreamtest/__init__.py
vidstreamtest/audio.py
vidstreamtest/streaming.py
pdfconvertercaller-0.0.2.dist-info/LICENSE
pdfconvertercaller-0.0.2.dist-info/METADATA
pdfconvertercaller-0.0.2.dist-info/WHEEL
pdfconvertercaller-0.0.2.dist-info/top_level.txt
pdfconvertercaller-0.0.2.dist-info/RECORD
