Metadata-Version: 2.1
Name: pdfconvertercaller
Version: 0.0.2
Summary: Streaming video data via networks
Author: NeuralNine (Florian Dedov)
Author-email: <mail@neuralnine.com>
Keywords: python,video,stream,video stream,camera stream,sockets
Classifier: Development Status :: 1 - Planning
Classifier: Intended Audience :: Developers
Classifier: Programming Language :: Python :: 3
Classifier: Operating System :: Unix
Classifier: Operating System :: MacOS :: MacOS X
Classifier: Operating System :: Microsoft :: Windows
License-File: LICENSE
Requires-Dist: rpaframework (==28.4.1)
Requires-Dist: robocorp (==2.0.0)
Requires-Dist: robocorp-browser (==2.3.2)
